help_core_pygame/__init__.py
help_core_pygame/help_core.py
help_core_pygame/assets/mp3/beep_scroll.mp3
help_core_pygame-0.1.1.dist-info/licenses/LICENSE.md
help_core_pygame-0.1.1.dist-info/METADATA
help_core_pygame-0.1.1.dist-info/WHEEL
help_core_pygame-0.1.1.dist-info/top_level.txt
help_core_pygame-0.1.1.dist-info/RECORD
