Metadata-Version: 2.4
Name: help-core-pygame
Version: 0.1.1
Summary: Help module for overlays and contextual help in Pygame
Author-email: Antonio Castr Snurmacher <acastro0841@gmail.com>
License-Expression: MIT
Project-URL: Homepage, https://github.com/acastr008/help_core_pygame
Project-URL: Source, https://github.com/acastr008/help_core_pygame
Project-URL: Issues, https://github.com/acastr008/help_core_pygame/issues
Keywords: pygame,help,overlay,games,ayuda
Classifier: Programming Language :: Python :: 3
Classifier: Operating System :: OS Independent
Classifier: Topic :: Games/Entertainment
Requires-Python: >=3.9
License-File: LICENSE.md
Requires-Dist: pygame>=2.0
Dynamic: license-file
